mosek_license/__init__.py
mosek_license_server-1.6.14.dist-info/METADATA
mosek_license_server-1.6.14.dist-info/WHEEL
mosek_license_server-1.6.14.dist-info/licenses/LICENSE
mosek_license_server-1.6.14.dist-info/RECORD
